[
    {
        "verse": "22_7:5",
        "meditations": [
            {
                "brand": "antantulla-appam",
                "title": "கர்மேல் மலை!",
                "filename": "1048.json"
            }
        ]
    },
    {
        "verse": "22_7:6",
        "meditations": [
            {
                "brand": "antantulla-appam",
                "title": "மனமகிழ்ச்சியினால் பிரியம்!",
                "filename": "921.json"
            }
        ]
    },
    {
        "verse": "22_7:13",
        "meditations": [
            {
                "brand": "antantulla-appam",
                "title": "புதிய கனிகள்!",
                "filename": "947.json"
            }
        ]
    }
]